bettersql/__init__.py
bettersql/sqldf.py
bettersql/sqldir.py
bettersql/test.py
bettersql-1.3.2.dist-info/LICENSE
bettersql-1.3.2.dist-info/METADATA
bettersql-1.3.2.dist-info/WHEEL
bettersql-1.3.2.dist-info/top_level.txt
bettersql-1.3.2.dist-info/RECORD
