Metadata-Version: 2.1
Name: bettersql
Version: 1.3.2
Summary: A package to use SQL with Pandas DataFrames, list and dict.
Home-page: UNKNOWN
Author: Joseph Gagliardo
Author-email: joey@me.com
License: UNKNOWN
Project-URL: Home Page, https://github.com/joegagliardo/bettersql
Keywords: python,sql,pandas,udf
Platform: UNKNOWN
Classifier: Development Status :: 5 - Production/Stable
Classifier: Intended Audience :: Education
Classifier: Intended Audience :: Developers
Classifier: Programming Language :: Python :: 3
Classifier: Operating System :: MacOS :: MacOS X
Classifier: Operating System :: POSIX :: Linux
Classifier: License :: OSI Approved :: Apache Software License
Requires-Dist: pandas
